pyinit_cli/__init__.py
pyinit_cli/cli.py
pyinit_cli/downloader.py
scripts/__init__.py
scripts/fmt.py
scripts/fmt_check.py
pyinit_cli-0.0.6.dist-info/METADATA
pyinit_cli-0.0.6.dist-info/WHEEL
pyinit_cli-0.0.6.dist-info/entry_points.txt
pyinit_cli-0.0.6.dist-info/top_level.txt
pyinit_cli-0.0.6.dist-info/RECORD
