Metadata-Version: 2.4
Name: pyinit-cli
Version: 0.0.6
Summary: Interactive Python project scaffolding tool
Author-email: Pradyoth S P <contact@pradyoth-sp.me>
License: MIT
Project-URL: Homepage, https://github.com/Pradyothsp/pyinit
Project-URL: Repository, https://github.com/Pradyothsp/pyinit
Project-URL: Issues, https://github.com/Pradyothsp/pyinit/issues
Keywords: python,project,scaffold,cli,generator
Classifier: Development Status :: 4 - Beta
Classifier: Intended Audience :: Developers
Classifier: License :: OSI Approved :: MIT License
Classifier: Operating System :: MacOS
Classifier: Operating System :: POSIX :: Linux
Classifier: Programming Language :: Python :: 3
Classifier: Programming Language :: Python :: 3.9
Classifier: Programming Language :: Python :: 3.10
Classifier: Programming Language :: Python :: 3.11
Classifier: Programming Language :: Python :: 3.12
Classifier: Programming Language :: Python :: 3.13
Classifier: Topic :: Software Development :: Code Generators
Classifier: Topic :: Software Development :: Libraries :: Python Modules
Requires-Python: >=3.9
Requires-Dist: requests>=2.25.0
